[{
    "artist": "Bad Habits",
    "title": "Ed Sheeran",
    "genre": "Synth-Pop",
    "year": "2021" 
},

{
    "artist": "Stay",
    "title": "The Kid LAROI, Justin Bieber",
    "genre": "Pop-Rock",
    "year": "2020" 
},

{
    "artist": "2002",
    "title": "Anne Marie",
    "genre": "Dance-Pop",
    "year": "2018" 
},

{
    "title": "Ashes",
    "artist": "Stellar",
    "genre": "Space-Rock",
    "year": "2020" 
},

{
    "title": "Bad Guy",
    "artist": "Billie Eilish",
    "genre": "Dance-Pop",
    "year": "2019" 
},

{
    "title": "Savage Love",
    "artist": "Jason Derulo, Jawsh 685",
    "genre": "Pop",
    "year": "2020" 
},

{
    "title": "Parachute",
    "artist": "John K",
    "genre": "Pop",
    "year": "2020" 
},

{
    "title": "Believer",
    "artist": "Imagine Dragons",
    "genre": "Pop-Rock",
    "year": "2017" 
},

{
    "title": "Checklist",
    "artist": "MAX (Feat, Chromeo)",
    "genre": "Dance-Pop",
    "year": "2019" 
},

{
    "title": "Eight",
    "artist": "IU",
    "genre": "K-Pop",
    "year": "2020" 
},

{
    "title": "Bad",
    "artist": "Christopher",
    "genre": "Electronic-Pop",
    "year": "2019" 
}]